sortedcountercpp-0.1.0.dist-info/RECORD
sortedcountercpp-0.1.0.dist-info/WHEEL
sortedcountercpp-0.1.0.dist-info/METADATA
sortedcountercpp-0.1.0.dist-info/licenses/LICENSE
sortedcounter/__init__.py
sortedcounter/sortedcounter.abi3.so
