Metadata-Version: 2.1
Name: SortedCounterCPP
Version: 0.1.0
Summary: Sorted version of collections.Counter, implemented in C++
Author-Email: JCGoran <jcgoran@protonmail.com>
Requires-Python: <3.14,>=3.9
Provides-Extra: dev
Provides-Extra: test
Requires-Dist: cmake-format; extra == "dev"
Requires-Dist: clang-format; extra == "dev"
Requires-Dist: numpy; extra == "test"
Requires-Dist: pytest; extra == "test"
